{"odds":[{"away_team_name":"Fiorentina","bookmaker_key":"onexbet","bookmaker_name":"1xBet","home_team_name":"Lecce","line_value":null,"market_key":"btts","match_date":"2026-04-20T18:45:00Z","match_external_id":"9439cff81cd6fd6de1e7046a3b49d8a8","odds_value":1.84,"selection_name":"Yes","snapshot_timestamp":"2026-04-20T18:45:00Z","sport_key":"soccer_italy_serie_a"},{"away_team_name":"Fiorentina","bookmaker_key":"onexbet","bookmaker_name":"1xBet","home_team_name":"Lecce","line_value":null,"market_key":"btts","match_date":"2026-04-20T18:45:00Z","match_external_id":"9439cff81cd6fd6de1e7046a3b49d8a8","odds_value":1.88,"selection_name":"No","snapshot_timestamp":"2026-04-20T18:45:00Z","sport_key":"soccer_italy_serie_a"},{"away_team_name":"Fiorentina","bookmaker_key":"williamhill","bookmaker_name":"William Hill","home_team_name":"Lecce","line_value":null,"market_key":"btts","match_date":"2026-04-20T18:45:00Z","match_external_id":"9439cff81cd6fd6de1e7046a3b49d8a8","odds_value":1.85,"selection_name":"Yes","snapshot_timestamp":"2026-04-20T18:45:00Z","sport_key":"soccer_italy_serie_a"},{"away_team_name":"Fiorentina","bookmaker_key":"williamhill","bookmaker_name":"William Hill","home_team_name":"Lecce","line_value":null,"market_key":"btts","match_date":"2026-04-20T18:45:00Z","match_external_id":"9439cff81cd6fd6de1e7046a3b49d8a8","odds_value":1.91,"selection_name":"No","snapshot_timestamp":"2026-04-20T18:45:00Z","sport_key":"soccer_italy_serie_a"}],"provider_payload":{"away_team":"Fiorentina","bookmakers":[{"key":"onexbet","markets":[{"key":"btts","last_update":"2026-04-15T17:47:12Z","outcomes":[{"name":"Yes","price":1.84},{"name":"No","price":1.88}]}],"title":"1xBet"},{"key":"williamhill","markets":[{"key":"btts","last_update":"2026-04-15T17:47:36Z","outcomes":[{"name":"Yes","price":1.85},{"name":"No","price":1.91}]}],"title":"William Hill"}],"commence_time":"2026-04-20T18:45:00Z","home_team":"Lecce","id":"9439cff81cd6fd6de1e7046a3b49d8a8","sport_key":"soccer_italy_serie_a","sport_title":"Serie A - Italy"},"response_metadata":{"method":"GET","request_url":"https://api.the-odds-api.com/v4/sports/soccer_italy_serie_a/events/9439cff81cd6fd6de1e7046a3b49d8a8/odds?apiKey=5f04d4d1d630b70ee92a71ea2ca7c283&markets=btts&oddsFormat=decimal&dateFormat=iso&regions=eu","response_headers":{"content-type":"application/json; charset=utf-8","x-requests-last":"1","x-requests-remaining":"422","x-requests-used":"78"},"status_code":200},"sport_key":"soccer_italy_serie_a"}